memra/__init__.py
memra/cli.py
memra/discovery.py
memra/discovery_client.py
memra/execution.py
memra/mcp_bridge_server.py
memra/models.py
memra/tool_registry.py
memra/tool_registry_client.py
memra/demos/ai_job_portal/__init__.py
memra/demos/ai_job_portal/ai_job_portal_demo.py
memra/demos/ai_job_portal/cleanup_demo.py
memra/demos/etl_invoice_processing/check_after_workflow.py
memra/demos/etl_invoice_processing/check_database.py
memra/demos/etl_invoice_processing/check_recent_db.py
memra/demos/etl_invoice_processing/database_monitor_agent.py
memra/demos/etl_invoice_processing/debug_mcp.py
memra/demos/etl_invoice_processing/debug_schema.py
memra/demos/etl_invoice_processing/etl_invoice_demo.py
memra/demos/etl_invoice_processing/modify_database.py
memra/demos/etl_invoice_processing/run_etl_batch.py
memra/demos/etl_invoice_processing/setup_demo_data.py
memra/demos/etl_invoice_processing/simple_pdf_processor.py
memra/demos/etl_invoice_processing/test_agent3.py
memra/demos/etl_invoice_processing/test_agent3_v2.py
memra/demos/etl_invoice_processing/test_api.py
memra/demos/etl_invoice_processing/test_api_client_direct.py
memra/demos/etl_invoice_processing/test_conversion.py
memra/demos/etl_invoice_processing/test_debug.py
memra/demos/etl_invoice_processing/test_direct_vision.py
memra/demos/etl_invoice_processing/test_full_response.py
memra/demos/etl_invoice_processing/test_memra_response.py
memra/demos/etl_invoice_processing/test_pdf_processor_response.py
memra/demos/etl_invoice_processing/test_pdfprocessor_direct.py
memra/demos/etl_invoice_processing/test_postgres_insert.py
memra/demos/etl_invoice_processing/test_remote_upload.py
memra/demos/etl_invoice_processing/test_schema_format.py
memra/demos/etl_invoice_processing/test_sql_executor.py
memra/demos/etl_invoice_processing/test_sql_executor_extra_fields.py
memra/demos/etl_invoice_processing/test_sql_executor_fix.py
memra/demos/etl_invoice_processing/test_updated_server.py
memra-0.2.29.dist-info/licenses/LICENSE
memra-0.2.29.dist-info/METADATA
memra-0.2.29.dist-info/WHEEL
memra-0.2.29.dist-info/entry_points.txt
memra-0.2.29.dist-info/top_level.txt
memra-0.2.29.dist-info/RECORD
