Metadata-Version: 2.4
Name: memra
Version: 0.2.29
Summary: Declarative framework for enterprise workflows with MCP integration - Client SDK
Home-page: https://github.com/memra/memra-sdk
Author: Memra
Author-email: Memra <support@memra.com>
License: MIT
Project-URL: Homepage, https://memra.co
Project-URL: Repository, https://github.com/memra-platform/memra-sdk
Classifier: Development Status :: 3 - Alpha
Classifier: Intended Audience :: Developers
Classifier: License :: OSI Approved :: MIT License
Classifier: Operating System :: OS Independent
Classifier: Programming Language :: Python :: 3
Classifier: Programming Language :: Python :: 3.8
Classifier: Programming Language :: Python :: 3.9
Classifier: Programming Language :: Python :: 3.10
Classifier: Programming Language :: Python :: 3.11
Requires-Python: >=3.8
License-File: LICENSE
Requires-Dist: pydantic>=1.8.0
Requires-Dist: httpx>=0.24.0
Requires-Dist: typing-extensions>=4.0.0
Requires-Dist: aiohttp>=3.8.0
Requires-Dist: aiohttp-cors>=0.7.0
Requires-Dist: requests>=2.25.0
Requires-Dist: huggingface-hub>=0.16.0
Requires-Dist: PyMuPDF>=1.21.0
Requires-Dist: python-dotenv>=0.19.0
Requires-Dist: psycopg2-binary>=2.9.0
Provides-Extra: dev
Requires-Dist: pytest>=6.0; extra == "dev"
Requires-Dist: pytest-asyncio; extra == "dev"
Requires-Dist: black; extra == "dev"
Requires-Dist: flake8; extra == "dev"
Provides-Extra: mcp
Requires-Dist: psycopg2-binary>=2.9.0; extra == "mcp"
Dynamic: author
Dynamic: home-page
Dynamic: license-file
Dynamic: requires-python
